mapc_suitability/.gitkeep
mapc_suitability/__init__.py
mapc_suitability/config.py
mapc_suitability/criteria_functions.py
mapc_suitability/main.py
mapc_suitability-0.2.12.dist-info/LICENSE
mapc_suitability-0.2.12.dist-info/METADATA
mapc_suitability-0.2.12.dist-info/WHEEL
mapc_suitability-0.2.12.dist-info/RECORD
