Metadata-Version: 2.3
Name: mapc_suitability
Version: 0.2.12
Summary: A python package for running suitability functions at MAPC
License: MIT
Author: RBowers
Author-email: rbowers@mapc.org
Requires-Python: >=3.11
Classifier: Programming Language :: Python :: 3
Classifier: Operating System :: OS Independent
Requires-Dist: folium (>=0.20.0,<0.21.0)
Requires-Dist: geopandas (>=1.1.1,<2.0.0)
Requires-Dist: mapclassify (>=2.10.0,<3.0.0)
Requires-Dist: matplotlib (>=3.10.5,<4.0.0)
Requires-Dist: networkx (>=3.5,<4.0)
Requires-Dist: numpy (>=2.3.2,<3.0.0)
Requires-Dist: openpyxl (>=3.1.5,<4.0.0)
Requires-Dist: osmnx (>=2.0.6,<3.0.0)
Requires-Dist: pandas (>=2.3.1,<3.0.0)
Requires-Dist: rasterio (>=1.4.3,<2.0.0)
Requires-Dist: rasterstats (>=0.20.0,<0.21.0)
Requires-Dist: shapely (>=2.1.1,<3.0.0)
Requires-Dist: xlrd (>=2.0.2,<3.0.0)
Requires-Dist: zipfile36 (>=0.1.3,<0.2.0)
Project-URL: Homepage, https://github.com/MAPC/mapc-suitability
Project-URL: Issues, https://github.com/MAPC/mapc-suitability/issues
